{
  "db_name": "PostgreSQL",
  "query": "SELECT id, email as \"email!\", phone, role as \"role!: UserRole\", \n           approval_status as \"approval_status!: ApprovalStatus\", \n           school_id, wallet_address\n           FROM user_profiles WHERE id = $1",
  "describe": {
    "columns": [
      {
        "ordinal": 0,
        "name": "id",
        "type_info": "Uuid"
      },
      {
        "ordinal": 1,
        "name": "email!",
        "type_info": "Varchar"
      },
      {
        "ordinal": 2,
        "name": "phone",
        "type_info": "Varchar"
      },
      {
        "ordinal": 3,
        "name": "role!: UserRole",
        "type_info": {
          "Custom": {
            "name": "user_role",
            "kind": {
              "Enum": [
                "student",
                "parent",
                "teacher",
                "school_admin",
                "school_head",
                "county_officer",
                "national_admin"
              ]
            }
          }
        }
      },
      {
        "ordinal": 4,
        "name": "approval_status!: ApprovalStatus",
        "type_info": {
          "Custom": {
            "name": "approval_status",
            "kind": {
              "Enum": [
                "pending",
                "approved",
                "rejected"
              ]
            }
          }
        }
      },
      {
        "ordinal": 5,
        "name": "school_id",
        "type_info": "Uuid"
      },
      {
        "ordinal": 6,
        "name": "wallet_address",
        "type_info": "Varchar"
      }
    ],
    "parameters": {
      "Left": [
        "Uuid"
      ]
    },
    "nullable": [
      true,
      true,
      true,
      true,
      true,
      true,
      true
    ]
  },
  "hash": "668b26462912abce3e9c05ae92a3a285ee205b516657c76c862c33210b0d0a7d"
}
